sphinxcontrib/autosaltsls/__init__.py
sphinxcontrib/autosaltsls/mapper.py
sphinxcontrib/autosaltsls/objects.py
sphinxcontrib/autosaltsls/templates/index.rst_t
sphinxcontrib/autosaltsls/templates/main.rst_t
sphinxcontrib/autosaltsls/templates/master.rst_t
sphinxcontrib/autosaltsls/templates/sls.rst_t
sphinxcontrib/autosaltsls/templates/top.rst_t
sphinxcontrib_autosaltsls-0.7.1.dist-info/LICENSE
sphinxcontrib_autosaltsls-0.7.1.dist-info/METADATA
sphinxcontrib_autosaltsls-0.7.1.dist-info/WHEEL
sphinxcontrib_autosaltsls-0.7.1.dist-info/top_level.txt
sphinxcontrib_autosaltsls-0.7.1.dist-info/RECORD
