Metadata-Version: 2.1
Name: sphinxcontrib-autosaltsls
Version: 0.7.1
Summary: Sphinx auto-document generator for SaltStack sls files
Home-page: https://github.com/Tanoti/sphinxcontrib-autosaltsls
Author: John Hicks
Author-email: john.p.hicks@gmail.com
License: Apache 2
Platform: UNKNOWN
Classifier: Development Status :: 3 - Alpha
Classifier: Framework :: Sphinx :: Extension
Classifier: Intended Audience :: System Administrators
Classifier: License :: OSI Approved :: Apache Software License
Classifier: Topic :: Documentation
Requires-Dist: Jinja2
Requires-Dist: sphinx (>=2.0.0)
